README.md
setup.py
heroku/__init__.py
heroku/account_manager.py
heroku/calls.py
heroku/db.py
heroku/errors.py
heroku_api.egg-info/PKG-INFO
heroku_api.egg-info/SOURCES.txt
heroku_api.egg-info/dependency_links.txt
heroku_api.egg-info/top_level.txt