Metadata-Version: 2.1
Name: heroku-api
Version: 0.1
Summary: Heroku api connector
Home-page: https://github.com/borisd93/heroku
Author: borisd93
Author-email: x93bd0@gmail.com
License: UNKNOWN
Platform: UNKNOWN
